MANIFEST.in
setup.py
Products/EXTERNALS.txt
Products/__init__.py
Products.kupu.egg-info/PKG-INFO
Products.kupu.egg-info/SOURCES.txt
Products.kupu.egg-info/dependency_links.txt
Products.kupu.egg-info/namespace_packages.txt
Products.kupu.egg-info/not-zip-safe
Products.kupu.egg-info/requires.txt
Products.kupu.egg-info/top_level.txt
Products/kupu/Makefile
Products/kupu/__init__.py
Products/kupu/config.py
Products/kupu/configure.zcml
Products/kupu/dist-apache-lenya.kupu
Products/kupu/dist-cnf.kupu
Products/kupu/dist-form.kupu
Products/kupu/dist-multi.kupu
Products/kupu/dist-plone.kupu
Products/kupu/dist-zope2.kupu
Products/kupu/dist.kupu
Products/kupu/i18n.bat
Products/kupu/include.kupu
Products/kupu/jslint.js
Products/kupu/jslint.opts
Products/kupu/kupu-i18nextract-sa-diff.patch
Products/kupu/kupu.xpr
Products/kupu/kupu_icon.gif
Products/kupu/lint.py
Products/kupu/make-jspx.xsl
Products/kupu/make.bat
Products/kupu/make.xsl
Products/kupu/refresh.txt
Products/kupu/version.txt
Products/kupu/Extensions/Install.py
Products/kupu/apache-lenya/README.txt
Products/kupu/apache-lenya/kupu/body.kupu
Products/kupu/apache-lenya/kupu/exit.kupu
Products/kupu/apache-lenya/kupu/include.kupu
Products/kupu/apache-lenya/kupu/kupudrawerstyles.css
Products/kupu/apache-lenya/kupu/kupustyles.css
Products/kupu/apache-lenya/kupu/lenya.js
Products/kupu/apache-lenya/kupu/lenya.kupu
Products/kupu/apache-lenya/kupu/toolbar.kupu
Products/kupu/apache-lenya/kupu/toolboxes.kupu
Products/kupu/apache-lenya/kupu/wire.kupu
Products/kupu/apache-lenya/kupu/xmlconfig.kupu
Products/kupu/apache-lenya/lenya/content2edit.xsl
Products/kupu/apache-lenya/lenya/i18n.xsl
Products/kupu/apache-lenya/lenya/kupumacros.xsl
Products/kupu/apache-lenya/lenya/kupusave.xsl
Products/kupu/apache-lenya/lenya/page2kupu.xsl
Products/kupu/apache-lenya/lenya/pageassets2kupulibrary.xsl
Products/kupu/apache-lenya/lenya/sitetree2kupulibrary.xsl
Products/kupu/apache-lenya/lenya/drawers/imagedrawer.xsl
Products/kupu/apache-lenya/lenya/drawers/imagelibraries.xml.jx
Products/kupu/apache-lenya/lenya/drawers/kupudrawerstyles.css
Products/kupu/apache-lenya/lenya/drawers/libraries.xml.jx
Products/kupu/apache-lenya/lenya/drawers/linkdrawer.xsl
Products/kupu/apache-lenya/lenya/drawers/linklibraries.xml.jx
