Metadata-Version: 1.0
Name: Products.kupu
Version: 1.5.2
Summary: UNKNOWN
Home-page: UNKNOWN
Author: Kupu Team
Author-email: kupu-dev@codespeak.net
License: Kupu License
Platform: UNKNOWN
Classifier: Framework :: Plone
Classifier: Programming Language :: Python
Classifier: Programming Language :: JavaScript
